<?xml version="1.0" encoding="UTF-8"?>
<Agent Id="EQ000001" View="СВЕРЛИЛЬНЫЙ" Group="2" Ip_address="192.168.2.2" Type="НАСТОЛЬНО-СВЕРЛИЛЬНЫЙ" Name="SV_NCV_164G2">
  <Parameter title="Price" value="9600000"> </Parameter> //Цена оборудования
  <Parameter title="Depreciation_Rate" value="6.67"  > </Parameter>//норма амортизации
  <Parameter title="CategoryCompRepairMechanParts" value="45" > </Parameter> //категория ремонтной сложности механической части
  <Parameter title="CategoryCompRepairElectrParts" value="10000"> </Parameter>//категория ремонтной сложности электрической части
  <Parameter title="NumberShifts" value="2"> </Parameter>//число смен работы станка
  <Parameter title="EnginePower" value="16"> </Parameter>//Установленная мощность электродвигателей (N)
  <Parameter title="FundWorkingTime" value="3890"> </Parameter>//эфективный фонд рабочего времени оборудования
  <Parameter title="KPD" value="0.85"> </Parameter> //КПД электродвигателей оборудования
</Agent>